<?xml version="1.0" encoding="iso-8859-1"?>
<Tabla Nombre="LOG_Stocks" Esquema="Logistica" Prefijo="STOCK">
  <Nombre>LOG_Stocks</Nombre>
  <Esquema>Logistica</Esquema>
  <Campos>
    <CCampo Identity="0" ForeignKey="1" PrimaryKey="1" xmlns="PERIO_Codigo">PERIO_Codigo</CCampo>
    <CCampo Identity="0" ForeignKey="1" PrimaryKey="1" xmlns="ARTIC_Codigo">ARTIC_Codigo</CCampo>
    <CCampo Identity="0" ForeignKey="1" PrimaryKey="1" xmlns="ALMAC_Id">ALMAC_Id</CCampo>
    <CCampo Identity="0" ForeignKey="0" PrimaryKey="1" xmlns="STOCK_Id">STOCK_Id</CCampo>
    <CCampo Identity="0" ForeignKey="1" PrimaryKey="0" xmlns="ENTID_CodigoProveedor">ENTID_CodigoProveedor</CCampo>
    <CCampo Identity="0" ForeignKey="1" PrimaryKey="0" xmlns="ENTID_CodigoCliente">ENTID_CodigoCliente</CCampo>
    <CCampo Identity="0" ForeignKey="1" PrimaryKey="0" xmlns="TIPOS_CodTipoDocEntrega">TIPOS_CodTipoDocEntrega</CCampo>
    <CCampo Identity="0" ForeignKey="1" PrimaryKey="0" xmlns="TIPOS_CodTipoUnidad">TIPOS_CodTipoUnidad</CCampo>
    <CCampo Identity="0" ForeignKey="0" PrimaryKey="0" xmlns="DOCCO_Codigo">DOCCO_Codigo</CCampo>
    <CCampo Identity="0" ForeignKey="0" PrimaryKey="0" xmlns="DOCCD_Item">DOCCD_Item</CCampo>
    <CCampo Identity="0" ForeignKey="1" PrimaryKey="0" xmlns="INGCO_Id">INGCO_Id</CCampo>
    <CCampo Identity="0" ForeignKey="1" PrimaryKey="0" xmlns="INGCD_Item">INGCD_Item</CCampo>
    <CCampo Identity="0" ForeignKey="1" PrimaryKey="0" xmlns="DOCVE_Codigo">DOCVE_Codigo</CCampo>
    <CCampo Identity="0" ForeignKey="1" PrimaryKey="0" xmlns="DOCVD_Item">DOCVD_Item</CCampo>
    <CCampo Identity="0" ForeignKey="1" PrimaryKey="0" xmlns="PEDID_Codigo">PEDID_Codigo</CCampo>
    <CCampo Identity="0" ForeignKey="1" PrimaryKey="0" xmlns="PDDET_Item">PDDET_Item</CCampo>
    <CCampo Identity="0" ForeignKey="0" PrimaryKey="0" xmlns="ORDCO_Codigo">ORDCO_Codigo</CCampo>
    <CCampo Identity="0" ForeignKey="1" PrimaryKey="0" xmlns="GUIAR_Codigo">GUIAR_Codigo</CCampo>
    <CCampo Identity="0" ForeignKey="1" PrimaryKey="0" xmlns="GUIRD_Item">GUIRD_Item</CCampo>
    <CCampo Identity="0" ForeignKey="1" PrimaryKey="0" xmlns="ORDEN_Codigo">ORDEN_Codigo</CCampo>
    <CCampo Identity="0" ForeignKey="1" PrimaryKey="0" xmlns="ORDET_Item">ORDET_Item</CCampo>
    <CCampo Identity="0" ForeignKey="1" PrimaryKey="0" xmlns="ORDEN_CodigoProduccion">ORDEN_CodigoProduccion</CCampo>
    <CCampo Identity="0" ForeignKey="1" PrimaryKey="0" xmlns="ORDET_ItemProduccion">ORDET_ItemProduccion</CCampo>
    <CCampo Identity="0" ForeignKey="1" PrimaryKey="0" xmlns="PEDID_CodigoTrans">PEDID_CodigoTrans</CCampo>
    <CCampo Identity="0" ForeignKey="1" PrimaryKey="0" xmlns="PEDID_Item">PEDID_Item</CCampo>
    <CCampo Identity="0" ForeignKey="0" PrimaryKey="0" xmlns="STOCK_Fecha">STOCK_Fecha</CCampo>
    <CCampo Identity="0" ForeignKey="0" PrimaryKey="0" xmlns="STOCK_CantidadIngreso">STOCK_CantidadIngreso</CCampo>
    <CCampo Identity="0" ForeignKey="0" PrimaryKey="0" xmlns="STOCK_CantidadSalida">STOCK_CantidadSalida</CCampo>
    <CCampo Identity="0" ForeignKey="0" PrimaryKey="0" xmlns="STOCK_Estado">STOCK_Estado</CCampo>
    <CCampo Identity="0" ForeignKey="0" PrimaryKey="0" xmlns="TIPOS_CodTipoMotivo">TIPOS_CodTipoMotivo</CCampo>
    <CCampo Identity="0" ForeignKey="1" PrimaryKey="0" xmlns="ARREG_Codigo">ARREG_Codigo</CCampo>
    <CCampo Identity="0" ForeignKey="1" PrimaryKey="0" xmlns="ARRDT_Item">ARRDT_Item</CCampo>
    <CCampo Identity="0" ForeignKey="0" PrimaryKey="0" xmlns="STOCK_UsrCrea">STOCK_UsrCrea</CCampo>
    <CCampo Identity="0" ForeignKey="0" PrimaryKey="0" xmlns="STOCK_FecCrea">STOCK_FecCrea</CCampo>
    <CCampo Identity="0" ForeignKey="0" PrimaryKey="0" xmlns="STOCK_UsrMod">STOCK_UsrMod</CCampo>
    <CCampo Identity="0" ForeignKey="0" PrimaryKey="0" xmlns="STOCK_FecMod">STOCK_FecMod</CCampo>
    <CCampo Identity="0" ForeignKey="0" PrimaryKey="0" xmlns="STOCK_Lote">STOCK_Lote</CCampo>
    <CCampo Identity="0" ForeignKey="0" PrimaryKey="0" xmlns="STOCK_Lote">STOCK_LoteGeneral</CCampo>
  </Campos>
  <CPrimarios>
    <CCampo Identity="0" ForeignKey="1" PrimaryKey="1" xmlns="PERIO_Codigo">PERIO_Codigo</CCampo>
    <CCampo Identity="0" ForeignKey="1" PrimaryKey="1" xmlns="ARTIC_Codigo">ARTIC_Codigo</CCampo>
    <CCampo Identity="0" ForeignKey="1" PrimaryKey="1" xmlns="ALMAC_Id">ALMAC_Id</CCampo>
    <CCampo Identity="0" ForeignKey="0" PrimaryKey="1" xmlns="STOCK_Id">STOCK_Id</CCampo>
  </CPrimarios>
  <CForaneos>
    <CCampo Identity="0" ForeignKey="0" PrimaryKey="0" xmlns="ALMAC_Id">ALMAC_Id</CCampo>
    <CCampo Identity="0" ForeignKey="0" PrimaryKey="0" xmlns="ARTIC_Codigo">ARTIC_Codigo</CCampo>
    <CCampo Identity="0" ForeignKey="0" PrimaryKey="0" xmlns="ENTID_Codigo">ENTID_Codigo</CCampo>
    <CCampo Identity="0" ForeignKey="0" PrimaryKey="0" xmlns="ENTID_Codigo">ENTID_Codigo</CCampo>
    <CCampo Identity="0" ForeignKey="0" PrimaryKey="0" xmlns="PERIO_Codigo">PERIO_Codigo</CCampo>
    <CCampo Identity="0" ForeignKey="0" PrimaryKey="0" xmlns="TIPOS_Codigo">TIPOS_Codigo</CCampo>
    <CCampo Identity="0" ForeignKey="0" PrimaryKey="0" xmlns="TIPOS_Codigo">TIPOS_Codigo</CCampo>
    <CCampo Identity="0" ForeignKey="0" PrimaryKey="0" xmlns="ALMAC_Id">ALMAC_Id</CCampo>
    <CCampo Identity="0" ForeignKey="0" PrimaryKey="0" xmlns="INGCO_Id">INGCO_Id</CCampo>
    <CCampo Identity="0" ForeignKey="0" PrimaryKey="0" xmlns="INGCD_Item">INGCD_Item</CCampo>
    <CCampo Identity="0" ForeignKey="0" PrimaryKey="0" xmlns="ARREG_Codigo">ARREG_Codigo</CCampo>
    <CCampo Identity="0" ForeignKey="0" PrimaryKey="0" xmlns="ARRDT_Item">ARRDT_Item</CCampo>
    <CCampo Identity="0" ForeignKey="0" PrimaryKey="0" xmlns="GUIAR_Codigo">GUIAR_Codigo</CCampo>
    <CCampo Identity="0" ForeignKey="0" PrimaryKey="0" xmlns="GUIRD_Item">GUIRD_Item</CCampo>
    <CCampo Identity="0" ForeignKey="0" PrimaryKey="0" xmlns="ORDEN_Codigo">ORDEN_Codigo</CCampo>
    <CCampo Identity="0" ForeignKey="0" PrimaryKey="0" xmlns="ORDET_Item">ORDET_Item</CCampo>
    <CCampo Identity="0" ForeignKey="0" PrimaryKey="0" xmlns="DOCVE_Codigo">DOCVE_Codigo</CCampo>
    <CCampo Identity="0" ForeignKey="0" PrimaryKey="0" xmlns="DOCVD_Item">DOCVD_Item</CCampo>
    <CCampo Identity="0" ForeignKey="0" PrimaryKey="0" xmlns="PEDID_Codigo">PEDID_Codigo</CCampo>
    <CCampo Identity="0" ForeignKey="0" PrimaryKey="0" xmlns="PDDET_Item">PDDET_Item</CCampo>
    <CCampo Identity="0" ForeignKey="0" PrimaryKey="0" xmlns="PEDID_CodigoTrans">PEDID_CodigoTrans</CCampo>
    <CCampo Identity="0" ForeignKey="0" PrimaryKey="0" xmlns="PEDID_Item">PEDID_Item</CCampo>
  </CForaneos>
  <CForaneosPrimarios>
    <CCampo Identity="0" ForeignKey="1" PrimaryKey="1" xmlns="PERIO_Codigo">PERIO_Codigo</CCampo>
    <CCampo Identity="0" ForeignKey="1" PrimaryKey="1" xmlns="ARTIC_Codigo">ARTIC_Codigo</CCampo>
    <CCampo Identity="0" ForeignKey="1" PrimaryKey="1" xmlns="ALMAC_Id">ALMAC_Id</CCampo>
  </CForaneosPrimarios>
</Tabla>